aichatlite/__init__.py
aichatlite/core/__init__.py
aichatlite/core/baseprompt.py
aichatlite/core/core.py
aichatlite/core/features/__init__.py
aichatlite/core/features/feature_main.py
aichatlite/core/features/handle_google_searchai.py
aichatlite/core/features/handle_pdf.py
aichatlite/core/omni_mixin.py
aichatlite/core/prompts.py
aichatlite/core/streamlit_app.py
aichatlite/core/streamlit_css.py
aichatlite/core/utils/__init__.py
aichatlite/core/utils/const.py
aichatlite/core/utils/prompt_names_fetcher.py
chat_gui.py
chat_run.py
aichatlite-0.3.0.dist-info/METADATA
aichatlite-0.3.0.dist-info/WHEEL
aichatlite-0.3.0.dist-info/entry_points.txt
aichatlite-0.3.0.dist-info/RECORD
